{
	"Warlord of the sea": "Shichibukai",
	"Warlord": "Shichibukai",
	"Dogstorm": "Inuarashi",
	"Cat viper": "Nekomamushi",
	"Rubber rubber": "Gomu gomu no",
	"Rubber-rubber": "Gomu gomu no",
	"Gum gum": "Gomu gomu no",
	"Gum-gum": "Gomu gomu no",
	"Celestial dragon": "Tenryuubito",
	"Transponder Snail": "Den Den Mushi",
	"Flying six": "Tobiroppo",
	"Red scabbard": "Akazaya",
	"Raccoon dog": "Tanuki",
	"Five Celestial Elder": "Gorosei",
	"Green bull": "Ryokugyu",
	"Red hound": "Akainu",
	"Black Horse": "Kurouma",
	"Wisteria Tiger": "Fujitora",
	"Purple Tiger": "Fujitora",
	"Yellow Monkey": "Kizaru",
	"Blue Pheasant": "Aokiji",
	"Emperor of the sea": "Yonko",
	"Emperors of the sea": "Yonkos",
	"Tempest Kick": "Rankyaku",
	"Moonwalk": "Geppo",
	"Six Sovereign Gun": "Rokuogan",
	"Iron Body": "Tekkai",
	"Shaving": "Soru",
	"Finger Pistol": "Shigan",
	"Paper Art": "Kami-e"
}